{"cameraMode":{"drawMode":0,"name":"Shaded","section":"Shading Mode"},"sceneLighting":false,"audioPlay":false,"sceneViewState":{"showFog":true,"showMaterialUpdate":false,"showSkybox":false,"showFlares":true,"showImageEffects":true,"showParticleSystems":true},"in2DMode":false,"pivot":{"x":36.45001220703125,"y":-21.274993896484376,"z":0.0},"rotation":{"x":-0.0030001418199390175,"y":-0.00599937979131937,"z":0.000018024064047494903,"w":-0.9999775290489197},"size":369.7433166503906,"orthographic":false}